tfquaternion/__init__.py
tfquaternion/auto_eval_testcase.py
tfquaternion/test_tfquaternion.py
tfquaternion/tfquaternion.py
tfquaternion-0.1.6.dist-info/LICENSE
tfquaternion-0.1.6.dist-info/METADATA
tfquaternion-0.1.6.dist-info/WHEEL
tfquaternion-0.1.6.dist-info/top_level.txt
tfquaternion-0.1.6.dist-info/RECORD
