Metadata-Version: 2.1
Name: tfquaternion
Version: 0.1.6
Summary: A differentiable quaternion implementation in tensorflow.
Home-page: https://github.com/PhilJd/tf-quaternion
Author: Philipp Jund
Author-email: jundp@cs.uni-freiburg.de
License: Apache 2.0
Keywords: quaternion tensorflow differentiable
Platform: UNKNOWN
Classifier: Development Status :: 3 - Alpha
Classifier: Intended Audience :: Developers
Classifier: Topic :: Scientific/Engineering
Classifier: License :: OSI Approved :: Apache Software License
Classifier: Programming Language :: Python :: 2
Classifier: Programming Language :: Python :: 2.7
Classifier: Programming Language :: Python :: 3
Classifier: Programming Language :: Python :: 3.4
Classifier: Programming Language :: Python :: 3.5
Classifier: Programming Language :: Python :: 3.6
Requires-Dist: numpy
